{"name":"Verificar el registro exitoso de un libro","id":"registrar-libros-en-la-biblioteca;verificar-el-registro-exitoso-de-un-libro","testSteps":[{"number":1,"description":"Dado que el administrador ha iniciado sesion en la Biblioteca","duration":7431,"startTime":"2026-06-11T20:54:23.357453500-05:00[America/Bogota]","screenshots":[{"screenshot":"4462e52e8a6a35e91ef87cb24552c13f69e42e66eab778de74d84f9c10712608.png","timeStamp":1781229270789}],"result":"SUCCESS","precondition":false,"level":0,"children":[{"number":2,"description":"Usuario abrir pagina","duration":4878,"startTime":"2026-06-11T20:54:23.373159300-05:00[America/Bogota]","screenshots":[{"screenshot":"ea4b75f30e19036543bc63b6ef091f23d0bf0725feb5e6fcd8577a161868c831.png","timeStamp":1781229268251}],"result":"SUCCESS","precondition":false,"level":1,"children":[{"number":3,"description":"usuario opens the Inicio","duration":4860,"startTime":"2026-06-11T20:54:23.379825800-05:00[America/Bogota]","screenshots":[{"screenshot":"ea4b75f30e19036543bc63b6ef091f23d0bf0725feb5e6fcd8577a161868c831.png","timeStamp":1781229268240}],"result":"SUCCESS","precondition":false,"level":2}]},{"number":4,"description":"Usuario autenticarse","duration":2333,"startTime":"2026-06-11T20:54:28.251980200-05:00[America/Bogota]","screenshots":[{"screenshot":"c91812304e3b824171e308b804c402d92409bb4e4851b1ad3f242d4dc7b714b4.png","timeStamp":1781229270584}],"result":"SUCCESS","precondition":false,"level":1,"children":[{"number":5,"description":"usuario enters \u0027admin@biblioteca.com\u0027 into campo email","duration":1040,"startTime":"2026-06-11T20:54:28.276049300-05:00[America/Bogota]","screenshots":[{"screenshot":"cd7a879b63bf054ea89cb68e67ec2c97b890a427922e8fde4c25306b4999ac1b.png","timeStamp":1781229269317}],"result":"SUCCESS","precondition":false,"level":2},{"number":6,"description":"usuario enters \u0027demo123\u0027 into campo contraseña","duration":690,"startTime":"2026-06-11T20:54:29.332843-05:00[America/Bogota]","screenshots":[{"screenshot":"9d1c2feb2c6d7e6665127d9373b6b3eba7825674215dd10b8fa45da07641f818.png","timeStamp":1781229270022}],"result":"SUCCESS","precondition":false,"level":2},{"number":7,"description":"usuario clicks on boton ingresar","duration":533,"startTime":"2026-06-11T20:54:30.022993300-05:00[America/Bogota]","screenshots":[{"screenshot":"c91812304e3b824171e308b804c402d92409bb4e4851b1ad3f242d4dc7b714b4.png","timeStamp":1781229270556}],"result":"SUCCESS","precondition":false,"level":2}]}]},{"number":8,"description":"Y que el administrador se encuentra en la pagina de libros","duration":618,"startTime":"2026-06-11T20:54:30.789030100-05:00[America/Bogota]","screenshots":[{"screenshot":"78dd635c1ef517122860ffb4d3b6df9a56c02bc7e2f3e2baf519933895ab81fa.png","timeStamp":1781229271407}],"result":"SUCCESS","precondition":false,"level":0,"children":[{"number":9,"description":"Usuario abrir modulo libros","duration":583,"startTime":"2026-06-11T20:54:30.810094200-05:00[America/Bogota]","screenshots":[{"screenshot":"78dd635c1ef517122860ffb4d3b6df9a56c02bc7e2f3e2baf519933895ab81fa.png","timeStamp":1781229271393}],"result":"SUCCESS","precondition":false,"level":1,"children":[{"number":10,"description":"usuario clicks on modulo libros","duration":557,"startTime":"2026-06-11T20:54:30.823465600-05:00[America/Bogota]","screenshots":[{"screenshot":"78dd635c1ef517122860ffb4d3b6df9a56c02bc7e2f3e2baf519933895ab81fa.png","timeStamp":1781229271381}],"result":"SUCCESS","precondition":false,"level":2}]}]},{"number":11,"description":"Cuando registra un nuevo libro con los siguientes datos\r\n| titulo | autor | isbn | cantidad |\r\n| Clean Code | Robert Martin | 9780132350884 | 5 |","duration":5165,"startTime":"2026-06-11T20:54:31.407128200-05:00[America/Bogota]","screenshots":[{"screenshot":"fce2c73236c7d2abe8c72d956fe35f2e9ced78121588e7016f753035a64951cb.png","timeStamp":1781229276572}],"result":"SUCCESS","precondition":false,"level":0,"children":[{"number":12,"description":"Usuario registrar libro","duration":5118,"startTime":"2026-06-11T20:54:31.421124100-05:00[America/Bogota]","screenshots":[{"screenshot":"fce2c73236c7d2abe8c72d956fe35f2e9ced78121588e7016f753035a64951cb.png","timeStamp":1781229276539}],"result":"SUCCESS","precondition":false,"level":1,"children":[{"number":13,"description":"usuario clicks on registrar libro","duration":501,"startTime":"2026-06-11T20:54:31.465725400-05:00[America/Bogota]","screenshots":[{"screenshot":"573857a9b98dde7f352674c00d5857f5aa8fc48450b1faadd6e055a54a7de14c.png","timeStamp":1781229271967}],"result":"SUCCESS","precondition":false,"level":2},{"number":14,"description":"usuario enters \u0027Libro_1781229271430\u0027 into campo titulo","duration":1307,"startTime":"2026-06-11T20:54:31.969567-05:00[America/Bogota]","screenshots":[{"screenshot":"8dea2ea252b78697476c6f603ee4ac8b1e985b744c33299319481ea074846a93.png","timeStamp":1781229273277}],"result":"SUCCESS","precondition":false,"level":2},{"number":15,"description":"usuario enters \u0027Robert Martin\u0027 into campo autor","duration":1103,"startTime":"2026-06-11T20:54:33.277204100-05:00[America/Bogota]","screenshots":[{"screenshot":"61d23a3fa498866b53bda50ccaf81990b1bf746c341c8d4bfc5e6baed48064d5.png","timeStamp":1781229274380}],"result":"SUCCESS","precondition":false,"level":2},{"number":16,"description":"usuario enters \u00271781229271441\u0027 into campo isbn","duration":980,"startTime":"2026-06-11T20:54:34.380405800-05:00[America/Bogota]","screenshots":[{"screenshot":"d3da5530a8a8e2295b7eb5b3229dad8d8f9298c8ebc457e0aa0c8a192ff2ee75.png","timeStamp":1781229275361}],"result":"SUCCESS","precondition":false,"level":2},{"number":17,"description":"usuario enters \u00275\u0027 into campo cantidad","duration":654,"startTime":"2026-06-11T20:54:35.363010800-05:00[America/Bogota]","screenshots":[{"screenshot":"3eebc15bccbd5d2abd9f1effbacb6a8f3228a4b22c7d77ffe5c2207ee332fdb5.png","timeStamp":1781229276017}],"result":"SUCCESS","precondition":false,"level":2},{"number":18,"description":"usuario clicks on boton guardar","duration":508,"startTime":"2026-06-11T20:54:36.017084-05:00[America/Bogota]","screenshots":[{"screenshot":"fce2c73236c7d2abe8c72d956fe35f2e9ced78121588e7016f753035a64951cb.png","timeStamp":1781229276526}],"result":"SUCCESS","precondition":false,"level":2}]}]},{"number":19,"description":"Entonces se debe verificar que el libro fue registrado correctamente","duration":205,"startTime":"2026-06-11T20:54:36.573854800-05:00[America/Bogota]","screenshots":[{"screenshot":"6d82c995e2a6da21630577023942790cdb6ff81cf375d6b9e970e25ef9b6d92f.png","timeStamp":1781229276779}],"result":"SUCCESS","precondition":false,"level":0,"children":[{"number":20,"description":"Then mensaje registro libro exitoso should be a string containing \u0027Libro registrado correctamente\u0027","duration":192,"startTime":"2026-06-11T20:54:36.577888200-05:00[America/Bogota]","screenshots":[{"screenshot":"6d82c995e2a6da21630577023942790cdb6ff81cf375d6b9e970e25ef9b6d92f.png","timeStamp":1781229276770}],"result":"SUCCESS","precondition":false,"level":1}]}],"userStory":{"id":"registrar-libros-en-la-biblioteca","storyName":"Registrar libros en la Biblioteca","path":"src/test/resources/features/registrarLibro.feature","type":"feature"},"featureTag":{"name":"Features/Registrar libros en la Biblioteca","type":"feature","displayName":"Features/Registrar libros en la Biblioteca"},"title":"Verificar el registro exitoso de un libro","backgroundTitle":"","backgroundDescription":"","tags":[{"name":"registroLibro","type":"tag","displayName":"registroLibro"},{"name":"Registrar libros en la Biblioteca","type":"feature","displayName":"Registrar libros en la Biblioteca"}],"startTime":"2026-06-11T20:54:23.346450700-05:00[America/Bogota]","duration":13439,"projectKey":"","sessionId":"7660b0652884c5ae76198c1c2deb8bad","driver":"chrome:usuario","isManualTestingUpToDate":false,"manual":false,"testSource":"Cucumber","actors":[{"name":"usuario","can":["browse the web"]}],"result":"SUCCESS"}